blend2stl/__init__.py
blend2stl/__main__.py
blend2stl-0.0.1.dist-info/licenses/LICENSE
blend2stl-0.0.1.dist-info/METADATA
blend2stl-0.0.1.dist-info/WHEEL
blend2stl-0.0.1.dist-info/entry_points.txt
blend2stl-0.0.1.dist-info/top_level.txt
blend2stl-0.0.1.dist-info/RECORD
