Metadata-Version: 2.4
Name: blend2stl
Version: 0.0.1
Summary: Export .blend files to .stl with scale
Author-email: Koziołek <bjkuczynski@gmail.com>
License-File: LICENSE
Requires-Dist: bpy
Dynamic: license-file
